LICENSE
MANIFEST.in
README.md
requirements.txt
setup.cfg
setup.py
ckanext/__init__.py
ckanext/openenergy/__init__.py
ckanext/openenergy/plugin.py
ckanext/openenergy/harvesters/README.md
ckanext/openenergy/harvesters/__init__.py
ckanext/openenergy/harvesters/ckanquery.py
ckanext/openenergy/public/base/images/ckan.ico
ckanext/openenergy/public/css/extra.css
ckanext/openenergy/templates/changelog.html
ckanext/openenergy/templates/footer.html
ckanext/openenergy/templates/header.html
ckanext/openenergy/templates/request_data.html
ckanext/openenergy/templates/home/snippets/promoted.html
ckanext_openenergy.egg-info/PKG-INFO
ckanext_openenergy.egg-info/SOURCES.txt
ckanext_openenergy.egg-info/dependency_links.txt
ckanext_openenergy.egg-info/entry_points.txt
ckanext_openenergy.egg-info/namespace_packages.txt
ckanext_openenergy.egg-info/top_level.txt