Metadata-Version: 2.1
Name: ckanext-openenergy
Version: 0.0.15
Summary: CKAN Customisations for the Open Energy project.
Home-page: https://github.com/openclimatefix/ckanext-openenergy
Author: Open Climate Fix
Author-email: info@openclimatefix.org
License: MIT
Keywords: CKAN theme open energy
Platform: UNKNOWN
Classifier: Development Status :: 3 - Alpha
Classifier: License :: OSI Approved :: MIT License
Classifier: Programming Language :: Python :: 2.7
